arraybuffer/__init__.pxd
arraybuffer/__init__.py
arraybuffer/arraybuffer.pxd
arraybuffer/arraybuffer.so
arraybuffer-0.1.1.dist-info/DESCRIPTION.rst
arraybuffer-0.1.1.dist-info/METADATA
arraybuffer-0.1.1.dist-info/metadata.json
arraybuffer-0.1.1.dist-info/RECORD
arraybuffer-0.1.1.dist-info/top_level.txt
arraybuffer-0.1.1.dist-info/WHEEL
