Metadata-Version: 2.0
Name: arraybuffer
Version: 0.1.1
Summary: Cython based buffer for arrays and typed memoryviews.
Home-page: https://bitbucket.org/intellimath/arraybuffer
Author: Zaur Shibzukhov
Author-email: szport@gmail.com
License: MIT License
Download-URL: https://bitbucket.org/intellimath/arraybuffer
Platform: UNKNOWN
Classifier: Development Status :: 4 - Beta
Classifier: Intended Audience :: Developers
Classifier: Intended Audience :: Information Technology
Classifier: License :: OSI Approved :: BSD License
Classifier: Programming Language :: Cython
Classifier: Programming Language :: Python :: 2
Classifier: Programming Language :: Python :: 2.7
Classifier: Programming Language :: Python :: 3
Classifier: Programming Language :: Python :: 3.3
Classifier: Programming Language :: Python :: 3.4
Classifier: Operating System :: OS Independent
Classifier: Topic :: Software Development :: Libraries :: Python Modules
